Markdown_Tracker-0.1.1.data/scripts/mdt
Markdown_Tracker-0.1.1.dist-info/DESCRIPTION.rst
Markdown_Tracker-0.1.1.dist-info/METADATA
Markdown_Tracker-0.1.1.dist-info/RECORD
Markdown_Tracker-0.1.1.dist-info/WHEEL
Markdown_Tracker-0.1.1.dist-info/metadata.json
Markdown_Tracker-0.1.1.dist-info/top_level.txt
mdt/__init__.py
mdt/mdt
mdt/mdt_diff.py
mdt/mdt_init.py
mdt/mdt_parse.py
mdt/mdt_stat.py
mdt/mdt_util.py
